verse/core/__init__.py
verse/core/_arg_parser.py
verse/core/_async_helper.py
verse/core/_component.py
verse/core/_context.py
verse/core/_data_accessor.py
verse/core/_decorators.py
verse/core/_dot_dict.py
verse/core/_loader.py
verse/core/_log_helper.py
verse/core/_ncall.py
verse/core/_operation.py
verse/core/_operation_parser.py
verse/core/_provider.py
verse/core/_response.py
verse/core/_type_converter.py
verse/core/_yaml_loader.py
verse/core/constants.py
verse/core/data_model.py
verse/core/dependency.py
verse/core/exceptions.py
verse/core/main.py
verse/core/manifest.py
verse/core/py.typed
verse/core/registry.yaml
verse/core/spec.py
verse/core/time.py
verse/internal/providers/hosted.py
verse/ql/__init__.py
verse/ql/_functions.py
verse/ql/_models.py
verse/ql/_parser_listener.py
verse/ql/_ql_parser.py
verse/ql/_query_processor.py
verse/ql/exceptions.py
verse/ql/generated/VerseQLLexer.interp
verse/ql/generated/VerseQLLexer.py
verse/ql/generated/VerseQLLexer.tokens
verse/ql/generated/VerseQLParser.interp
verse/ql/generated/VerseQLParser.py
verse/ql/generated/VerseQLParser.tokens
verse/ql/generated/VerseQLParserListener.py
verse/ql/grammar/VerseQLLexer.g4
verse/ql/grammar/VerseQLParser.g4
verse/ql/py.typed
verse_core-0.0.33.dist-info/LICENSE
verse_core-0.0.33.dist-info/METADATA
verse_core-0.0.33.dist-info/WHEEL
verse_core-0.0.33.dist-info/entry_points.txt
verse_core-0.0.33.dist-info/RECORD
