Metadata-Version: 2.3
Name: verse-core
Version: 0.0.33
Summary: Verse Core
License: MIT
Keywords: verse,core
Author: Verse
Author-email: admin@rapidverse.com
Requires-Python: >=3.9
Classifier: License :: OSI Approved :: MIT License
Classifier: Programming Language :: Python :: 3
Classifier: Programming Language :: Python :: 3.9
Classifier: Programming Language :: Python :: 3.10
Classifier: Programming Language :: Python :: 3.11
Classifier: Programming Language :: Python :: 3.12
Classifier: Programming Language :: Python :: 3.13
Requires-Dist: PyYAML
Requires-Dist: antlr4-python3-runtime
Requires-Dist: docstring_parser
Requires-Dist: pydantic
Project-URL: Documentation, https://github.com/rapidverse/verse
Project-URL: Homepage, https://github.com/rapidverse/verse
Project-URL: Repository, https://github.com/rapidverse/verse
